hardpy/__init__.py
hardpy/cli/__init__.py
hardpy/cli/cli.py
hardpy/cli/template.py
hardpy/common/__init__.py
hardpy/common/config.py
hardpy/common/singleton.py
hardpy/common/stand_cloud/__init__.py
hardpy/common/stand_cloud/connector.py
hardpy/common/stand_cloud/exception.py
hardpy/common/stand_cloud/oauth2.py
hardpy/common/stand_cloud/registration.py
hardpy/common/stand_cloud/token_manager.py
hardpy/common/stand_cloud/utils.py
hardpy/hardpy_panel/__init__.py
hardpy/hardpy_panel/api.py
hardpy/hardpy_panel/frontend/dist/favicon.ico
hardpy/hardpy_panel/frontend/dist/index.html
hardpy/hardpy_panel/frontend/dist/logo192.png
hardpy/hardpy_panel/frontend/dist/logo512.png
hardpy/hardpy_panel/frontend/dist/manifest.json
hardpy/hardpy_panel/frontend/dist/assets/allPaths-BXbcAtew.js
hardpy/hardpy_panel/frontend/dist/assets/allPathsLoader-lJLHMNNZ.js
hardpy/hardpy_panel/frontend/dist/assets/blueprint-icons-16-B2twAPZE.ttf
hardpy/hardpy_panel/frontend/dist/assets/blueprint-icons-16-C0Unyq1d.eot
hardpy/hardpy_panel/frontend/dist/assets/blueprint-icons-16-CVy9qFng.svg
hardpy/hardpy_panel/frontend/dist/assets/blueprint-icons-16-Ck1ifK4A.woff
hardpy/hardpy_panel/frontend/dist/assets/blueprint-icons-16-DwWyHYRo.woff2
hardpy/hardpy_panel/frontend/dist/assets/blueprint-icons-20-9zitLjlL.woff2
hardpy/hardpy_panel/frontend/dist/assets/blueprint-icons-20-CjKGIKxE.woff
hardpy/hardpy_panel/frontend/dist/assets/blueprint-icons-20-DQ09GSQq.svg
hardpy/hardpy_panel/frontend/dist/assets/blueprint-icons-20-DmR755bS.ttf
hardpy/hardpy_panel/frontend/dist/assets/blueprint-icons-20-p9MhBXD8.eot
hardpy/hardpy_panel/frontend/dist/assets/browser-ponyfill-DzwgrUwX.js
hardpy/hardpy_panel/frontend/dist/assets/index-B-fsa5Ru.js
hardpy/hardpy_panel/frontend/dist/assets/index-B7T9xvaW.css
hardpy/hardpy_panel/frontend/dist/assets/index-CVhA7vmQ.js
hardpy/hardpy_panel/frontend/dist/assets/index-DLOviMB1.js
hardpy/hardpy_panel/frontend/dist/assets/logo_smol-CK3jE85c.png
hardpy-0.20.0.dist-info/METADATA
hardpy-0.20.0.dist-info/WHEEL
hardpy-0.20.0.dist-info/entry_points.txt
hardpy-0.20.0.dist-info/licenses/LICENSE
hardpy-0.20.0.dist-info/RECORD
