Metadata-Version: 2.4
Name: hardpy
Version: 0.20.0
Summary: HardPy library for device testing
Project-URL: Homepage, https://github.com/everypinio/hardpy/
Project-URL: Documentation, https://everypinio.github.io/hardpy/
Project-URL: Repository, https://github.com/everypinio/hardpy/
Project-URL: Changelog, https://everypinio.github.io/hardpy/changelog/
Author-email: Everypin <info@everypin.io>
License-Expression: GPL-3.0-or-later
License-File: LICENSE
Classifier: Development Status :: 4 - Beta
Classifier: Framework :: Pytest
Classifier: Intended Audience :: Developers
Classifier: Operating System :: OS Independent
Classifier: Programming Language :: Python :: 3
Classifier: Programming Language :: Python :: 3 :: Only
Classifier: Programming Language :: Python :: 3.10
Classifier: Programming Language :: Python :: 3.11
Classifier: Programming Language :: Python :: 3.12
Classifier: Programming Language :: Python :: 3.13
Classifier: Topic :: Software Development :: Libraries
Classifier: Topic :: Software Development :: Testing
Classifier: Topic :: Software Development :: Testing :: Acceptance
Classifier: Topic :: Utilities
Requires-Python: >=3.10
Requires-Dist: fastapi>=0.100.1
Requires-Dist: glom>=23.3.0
Requires-Dist: jinja2<4,>=3
Requires-Dist: keyring<26,>=25.0.0
Requires-Dist: natsort>=8.4.0
Requires-Dist: oauthlib<4,>=3.1.0
Requires-Dist: py-machineid~=0.6.0
Requires-Dist: pycouchdb<2,>=1.14.2
Requires-Dist: pydantic<3,>=2.4.0
Requires-Dist: pytest>=7
Requires-Dist: qrcode>=8
Requires-Dist: requests-oauth2client<2,>=1.5.0
Requires-Dist: requests-oauthlib<3,>=2.0.0
Requires-Dist: requests<3,>=2.30.0
Requires-Dist: tomli-w<2,>=1.1.0
Requires-Dist: tomli<3,>=2.0.1
Requires-Dist: typer<1,>=0.12
Requires-Dist: tzlocal~=5.2
Requires-Dist: uuid6
Requires-Dist: uvicorn>=0.23.2
Provides-Extra: build
Requires-Dist: build==1.0.3; extra == 'build'
Provides-Extra: dev
Requires-Dist: mypy>=1.11.0; extra == 'dev'
Requires-Dist: ruff==0.8.0; extra == 'dev'
Requires-Dist: wemake-python-styleguide>=0.19.2; extra == 'dev'
Provides-Extra: tests
Requires-Dist: psutil~=7.0.0; extra == 'tests'
Requires-Dist: pytest-timeout==2.4.0; extra == 'tests'
